pcalendar/__init__.py
pcalendar/pcalendar.py
pcalendar-1.1.0.dist-info/licenses/LICENSE
pcalendar-1.1.0.dist-info/METADATA
pcalendar-1.1.0.dist-info/WHEEL
pcalendar-1.1.0.dist-info/top_level.txt
pcalendar-1.1.0.dist-info/RECORD
