Metadata-Version: 2.4
Name: pcalendar
Version: 1.1.0
Summary: Persian Calendar Library - Python Implementation for Solar Hijri Calendar
Home-page: https://codeberg.org/alimiracle/pcalendar
Author: Ali Miracle
Author-email: Ali Miracle <alimiracle@riseup.net>
Maintainer-email: Ali Miracle <alimiracle@riseup.net>
License: GPL-3.0-or-later
Project-URL: Homepage, https://codeberg.org/alimiracle/pcalendar
Project-URL: Repository, https://codeberg.org/alimiracle/pcalendar
Project-URL: Bug Reports, https://codeberg.org/alimiracle/pcalendar
Project-URL: Documentation, https://codeberg.org/alimiracle/pcalendar#readme
Keywords: persian,calendar,solar,hijri,shamsi,date,time,conversion
Classifier: Development Status :: 5 - Production/Stable
Classifier: Intended Audience :: Developers
Classifier: License :: OSI Approved :: GNU General Public License v3 (GPLv3)
Classifier: Operating System :: OS Independent
Classifier: Programming Language :: Python :: 3
Classifier: Programming Language :: Python :: 3.7
Classifier: Programming Language :: Python :: 3.8
Classifier: Programming Language :: Python :: 3.9
Classifier: Programming Language :: Python :: 3.10
Classifier: Programming Language :: Python :: 3.11
Classifier: Programming Language :: Python :: 3.12
Classifier: Topic :: Software Development :: Libraries :: Python Modules
Classifier: Topic :: Software Development :: Localization
Classifier: Topic :: Utilities
Requires-Python: >=3.7
License-File: LICENSE
Provides-Extra: dev
Requires-Dist: pytest>=6.0; extra == "dev"
Requires-Dist: pytest-cov>=2.10; extra == "dev"
Requires-Dist: black>=21.0; extra == "dev"
Requires-Dist: flake8>=3.8; extra == "dev"
Requires-Dist: mypy>=0.800; extra == "dev"
Provides-Extra: test
Requires-Dist: pytest>=6.0; extra == "test"
Requires-Dist: pytest-cov>=2.10; extra == "test"
Dynamic: author
Dynamic: home-page
Dynamic: license-file
Dynamic: requires-python
